dotplotter/__init__.py
dotplotter/check_input.py
dotplotter/chunks.py
dotplotter/main.py
dotplotter/parser.py
dotplotter-1.0.1.dist-info/LICENSE
dotplotter-1.0.1.dist-info/METADATA
dotplotter-1.0.1.dist-info/WHEEL
dotplotter-1.0.1.dist-info/entry_points.txt
dotplotter-1.0.1.dist-info/top_level.txt
dotplotter-1.0.1.dist-info/RECORD
