Metadata-Version: 2.2
Name: dotplotter
Version: 1.0.1
Summary: A python for plotting dot plots from blast results.
Home-page: https://github.com/DrBoothTJ/dotplotter
Author: Thomas J. Booth
Author-email: thoboo@biosustain.dtu.dk
License: GNU General Public License v3.0
Requires-Python: >=3.7
License-File: LICENSE
Requires-Dist: matplotlib
Dynamic: author
Dynamic: author-email
Dynamic: description
Dynamic: description-content-type
Dynamic: home-page
Dynamic: license
Dynamic: requires-dist
Dynamic: requires-python
Dynamic: summary
